__init__.py
autoindex.py
constants.py
modules/__init__.py
modules/bookmarks.py
autoindex-0.3.0.dist-info/METADATA
autoindex-0.3.0.dist-info/WHEEL
autoindex-0.3.0.dist-info/entry_points.txt
autoindex-0.3.0.dist-info/top_level.txt
autoindex-0.3.0.dist-info/RECORD
