Metadata-Version: 2.1
Name: autoindex
Version: 0.3.0
Summary: A cli tool to automatically add bookmarks to PDFs
Home-page: https://github.com/Suyash458/autoindex
Author: Suyash Behera
Author-email: sne9x@outlook.com
License: UNKNOWN
Download-URL: https://github.com/Suyash458/autoindex/archive/master.zip
Keywords: PDF,PyPDF,pdfminer,bookmarks,cli
Platform: UNKNOWN
Requires-Dist: Click
Requires-Dist: pdfminer.six
Requires-Dist: PyPDF2
